{
  "$schema": "https://static.modelcontextprotocol.io/schemas/2025-12-11/server.schema.json",
  "name": "io.github.MackinHung/taiwan-hospital",
  "description": "5 tools for NHI healthcare facility lookup",
  "version": "1.0.1",
  "packages": [
    {
      "registryType": "npm",
      "identifier": "@formosa-mcp/taiwan-hospital",
      "version": "1.0.1",
      "transport": {
        "type": "stdio"
      }
    }
  ],
  "repository": {
    "url": "https://github.com/MackinHung/taiwan-mcp-platform",
    "source": "github",
    "id": "MackinHung/taiwan-mcp-platform",
    "subfolder": "servers/taiwan-hospital"
  },
  "websiteUrl": "https://formosa-mcp-platform.pages.dev/server.html?slug=taiwan-hospital",
  "license": "AGPL-3.0"
}
